Metadata-Version: 2.1
Name: detectron2-cdo
Version: 0.5
Summary: Detectron2 is FAIR's next-generation research platform for object detection and segmentation.
Home-page: https://github.com/facebookresearch/detectron2
Author: FAIR
License: UNKNOWN
Platform: UNKNOWN
Requires-Python: >=3.6
Provides-Extra: all
Provides-Extra: dev
License-File: LICENSE
